pycloudevents-0.1.4.dist-info/METADATA
pycloudevents-0.1.4.dist-info/WHEEL
pycloudevents-0.1.4.dist-info/licenses/LICENSE
pycloudevents/__init__.py
pycloudevents/cloudevent.py
pycloudevents/exceptions.py
pycloudevents-0.1.4.dist-info/RECORD
