Metadata-Version: 2.1
Name: pycloudevents
Version: 0.1.4
Summary: A third party cloudevents 1.0 SDK for Python.
Keywords: cloudevents
Author-Email: -LAN- <laipz8200@outlook.com>
License: Apache2.0
Project-URL: Homepage, https://github.com/laipz8200/pycloudevents
Project-URL: Repository, https://github.com/laipz8200/pycloudevents
Project-URL: Documentation, https://github.com/laipz8200/pycloudevents/blob/main/README.md
Project-URL: Changelog, https://github.com/laipz8200/pycloudevents/blob/main/CHANGELOG.md
Requires-Python: >=3.11
